LICENSE
MANIFEST.in
README.rst
setup.py
smsl.py
smsl.egg-info/PKG-INFO
smsl.egg-info/SOURCES.txt
smsl.egg-info/dependency_links.txt
smsl.egg-info/entry_points.txt
smsl.egg-info/pbr.json
smsl.egg-info/requires.txt
smsl.egg-info/top_level.txt