Metadata-Version: 1.0
Name: smsl
Version: 0.7
Summary: Tool for sending SMS via HTML SMSlink
Home-page: https://github.com/lorchel/smsl
Author: Tom Richter
Author-email: lorchel@gmx.de
License: MIT
Keywords: send,sms,mail
Platform: OS Independent
